redisearchtables-0.0.1.dist-info/METADATA
redisearchtables-0.0.1.dist-info/WHEEL
redisearchtables/__init__.py
redisearchtables/redisearchtables.cpython-311-x86_64-linux-gnu.so
redisearchtables-0.0.1.dist-info/RECORD
