Metadata-Version: 2.3
Name: redisearchtables
Version: 0.0.1
Classifier: Programming Language :: Rust
Classifier: Programming Language :: Python :: Implementation :: CPython
Classifier: Programming Language :: Python :: Implementation :: PyPy
Summary: Manage RediSearch indexes in a SQLAlchemy-like manner
Author-email: "Diviyan K." <diviyan@fentech.ai>
Requires-Python: >=3.8
